duppy/__init__.py
duppy/__main__.py
duppy/duppy
duppy/duppy.py
duppy/duppy_indexer.py
duppy/duppy_rules.py
duppy-0.1.0.dist-info/LICENSE
duppy-0.1.0.dist-info/METADATA
duppy-0.1.0.dist-info/WHEEL
duppy-0.1.0.dist-info/entry_points.txt
duppy-0.1.0.dist-info/RECORD
