Metadata-Version: 2.3
Name: duppy
Version: 0.1.0
Summary: duplicate file finder
License: MIT
Keywords: duplicates
Author: Bart
Author-email: scarfboy@gmail.com
Requires-Python: >=3
Classifier: Programming Language :: Python :: 3
Classifier: License :: OSI Approved :: MIT License
Project-URL: Homepage, https://github.com/knobs-dials/duppy
Project-URL: Repository, https://github.com/knobs-dials/duppy
